poof/__init__.py
poof/core.py
poof/launchd.py
poof/nukedir.py
poof-1.5.0.dist-info/licenses/LICENSE.txt
poof-1.5.0.dist-info/METADATA
poof-1.5.0.dist-info/WHEEL
poof-1.5.0.dist-info/entry_points.txt
poof-1.5.0.dist-info/top_level.txt
poof-1.5.0.dist-info/RECORD
