Metadata-Version: 2.4
Name: poof
Version: 1.5.0
Summary: poof backup - instant, secure backup to a cloud drive
Author-email: The poof-backup dev team <poof.project@cime.net>
License-Expression: BSD-3-Clause
Classifier: Intended Audience :: Other Audience
Classifier: Operating System :: MacOS
Classifier: Operating System :: Unix
Classifier: Programming Language :: Python :: 3
Classifier: Programming Language :: Python :: 3.7
Classifier: Topic :: System :: Archiving :: Backup
Classifier: Topic :: Utilities
Requires-Python: >=3.7
License-File: LICENSE.txt
Requires-Dist: appdirs
Requires-Dist: click
Requires-Dist: psutil
Requires-Dist: pyperclip
Dynamic: license-file
